statuscake_api/__init__.py
statuscake_api/client.py
statuscake_api/config.py
statuscake_api/exceptions.py
statuscake_api-0.1.1.dist-info/LICENSE
statuscake_api-0.1.1.dist-info/METADATA
statuscake_api-0.1.1.dist-info/WHEEL
statuscake_api-0.1.1.dist-info/top_level.txt
statuscake_api-0.1.1.dist-info/RECORD
