Metadata-Version: 2.1
Name: statuscake-api
Version: 0.1.1
Summary: "Statuscake API v1 wrapper"
Home-page: https://github.com/alkivi-sas/python-statuscake-api
Author: Anthony Martinet
Author-email: anthony@alkivi.fr
License: LGPL
Keywords: statuscake,sdk,rest
Platform: UNKNOWN
Classifier: License :: OSI Approved :: GNU Lesser General Public License v3 (LGPLv3)
Classifier: Development Status :: 4 - Beta
Classifier: Intended Audience :: Developers
Classifier: Operating System :: OS Independent
Classifier: Programming Language :: Python
Classifier: Programming Language :: Python :: 3
Classifier: Programming Language :: Python :: 3.6
Classifier: Programming Language :: Python :: 3.7
Classifier: Topic :: Software Development :: Libraries :: Python Modules
License-File: LICENSE
Requires-Dist: requests
